README.md
setup.py
dict2dataframe/__init__.py
dict2dataframe/core.py
dict2dataframe/handlers.py
dict2dataframe/settings.py
dict2dataframe.egg-info/PKG-INFO
dict2dataframe.egg-info/SOURCES.txt
dict2dataframe.egg-info/dependency_links.txt
dict2dataframe.egg-info/requires.txt
dict2dataframe.egg-info/top_level.txt